Workbook
Name Routes: Settings!$A$2:$A$100
Name Stores: Settings!$C$2:$C$500
Name ExpenseCategories: Settings!$E$2:$E$100
Name SaleTypes: Settings!$G$2:$G$3
Name PaymentMethods: Settings!$H$2:$H$3

Sheet README_Setup
A1: Google Sheets dropdown setup / ตั้งค่า dropdown
A3: After importing this file into Google Sheets, click a Route or Store cell.
A4: If you do NOT see a dropdown arrow, re-apply validation once per column:
A6: Route_Sales
A7: Column B (Route): Data → Data validation → Dropdown from a range → Routes
A8: Column C (Store): … → Stores
A9: Column E (Sale type): … → SaleTypes
A11: Store_Payments
A12: Column B (Store): … → Stores
A13: Column D (Payment): … → PaymentMethods
A15: Expenses
A16: Column B (Category): … → ExpenseCategories
... A26: then Run → applyLedgerValidations (one-time fix).

Sheet Settings
A1: Routes / เส้นทาง | C1: Stores / ร้านค้า | E1: Expense categories / หมวดค่าใช้จ่าย | G1: Sale type / ประเภทการขาย | H1: Payment method / ช่องทางจ่าย
A2: Route_01 | C2: Store_01 | E2: Water | F2: Production | G2: Cash | H2: Cash
A3: Route_02 | C3: Store_02 | E3: Power | F3: Production | G3: Credit | H3: Bank
A4: Route_03 | C4: Store_03 | E4: Bags | F4: Production
A5: Route_04 | C5: Store_04 | E5: Machine repair | F5: Production
A6: Route_05 | C6: Store_05 | E6: Fuel | F6: Distribution
A7: Route_06 | C7: Store_06 | E7: Vehicle repair | F7: Distribution
C8: Store_07 | E8: Driver pay | F8: Distribution
C9: Store_08 | E9: Rent | F9: Overhead
C10: Store_09 | E10: Permits | F10: Overhead
C11: Store_10 | E11: Insurance | F11: Overhead
E12: Other | F12: Overhead

Sheet Route_Sales
A1: Date / วันที่ | B1: Route / เส้นทาง | C1: Store / ร้าน | D1: Bags / ถุง | E1: Sale type / สดหรือค้างจ่าย | F1: Amount (฿) / จำนวนเงิน | G1: Notes / หมายเหตุ
A2: 2026-06-16 | B2: Route_01 | C2: Store_01 | D2: 10 | E2: Cash | F2: 300
A3: 2026-06-16 | B3: Route_01 | C3: Store_02 | D3: 8 | E3: Credit | F3: 240

Sheet Store_Payments
A1: Date / วันที่ | B1: Store / ร้าน | C1: Amount paid (฿) / จำนวนที่จ่าย | D1: Payment method / ช่องทางจ่าย | E1: Notes / หมายเหตุ
A2: 2026-06-20 | B2: Store_02 | C2: 240 | D2: Cash | E2: Paid in full

Sheet Store_Balances
A1: Read-only / อ่านอย่างเดียว — who owes what / ลูกค้าค้างจ่าย
A2: Store / ร้าน | B2: Opening debt (฿) / ยอดยกมา | C2: Credit sales (฿) / ขายเชื่อ | D2: Payments (฿) / รับชำระ | E2: Still owed (฿) / คงค้าง
A3: Store_01 | B3: =IFERROR(SUMIF(Opening_Balances!$A:$A,A3,Opening_Balances!$B:$B),0) | C3: =SUMIFS(Route_Sales!$F:$F,Route_Sales!$C:$C,A3,Route_Sales!$E:$E,"Credit") | D3: =SUMIF(Store_Payments!$B:$B,A3,Store_Payments!$C:$C) | E3: =B3+C3-D3
A4: Store_02 | B4: =IFERROR(SUMIF(Opening_Balances!$A:$A,A4,Opening_Balances!$B:$B),0) | C4: =SUMIFS(Route_Sales!$F:$F,Route_Sales!$C:$C,A4,Route_Sales!$E:$E,"Credit") | D4: =SUMIF(Store_Payments!$B:$B,A4,Store_Payments!$C:$C) | E4: =B4+C4-D4
A5: Store_03 | B5: =IFERROR(SUMIF(Opening_Balances!$A:$A,A5,Opening_Balances!$B:$B),0) | C5: =SUMIFS(Route_Sales!$F:$F,Route_Sales!$C:$C,A5,Route_Sales!$E:$E,"Credit") | D5: =SUMIF(Store_Payments!$B:$B,A5,Store_Payments!$C:$C) | E5: =B5+C5-D5
A6: Store_04 | B6: =IFERROR(SUMIF(Opening_Balances!$A:$A,A6,Opening_Balances!$B:$B),0) | C6: =SUMIFS(Route_Sales!$F:$F,Route_Sales!$C:$C,A6,Route_Sales!$E:$E,"Credit") | D6: =SUMIF(Store_Payments!$B:$B,A6,Store_Payments!$C:$C) | E6: =B6+C6-D6
A7: Store_05 | B7: =IFERROR(SUMIF(Opening_Balances!$A:$A,A7,Opening_Balances!$B:$B),0) | C7: =SUMIFS(Route_Sales!$F:$F,Route_Sales!$C:$C,A7,Route_Sales!$E:$E,"Credit") | D7: =SUMIF(Store_Payments!$B:$B,A7,Store_Payments!$C:$C) | E7: =B7+C7-D7
A8: Store_06 | B8: =IFERROR(SUMIF(Opening_Balances!$A:$A,A8,Opening_Balances!$B:$B),0) | C8: =SUMIFS(Route_Sales!$F:$F,Route_Sales!$C:$C,A8,Route_Sales!$E:$E,"Credit") | D8: =SUMIF(Store_Payments!$B:$B,A8,Store_Payments!$C:$C) | E8: =B8+C8-D8
A9: Store_07 | B9: =IFERROR(SUMIF(Opening_Balances!$A:$A,A9,Opening_Balances!$B:$B),0) | C9: =SUMIFS(Route_Sales!$F:$F,Route_Sales!$C:$C,A9,Route_Sales!$E:$E,"Credit") | D9: =SUMIF(Store_Payments!$B:$B,A9,Store_Payments!$C:$C) | E9: =B9+C9-D9
A10: Store_08 | B10: =IFERROR(SUMIF(Opening_Balances!$A:$A,A10,Opening_Balances!$B:$B),0) | C10: =SUMIFS(Route_Sales!$F:$F,Route_Sales!$C:$C,A10,Route_Sales!$E:$E,"Credit") | D10: =SUMIF(Store_Payments!$B:$B,A10,Store_Payments!$C:$C) | E10: =B10+C10-D10
A11: Store_09 | B11: =IFERROR(SUMIF(Opening_Balances!$A:$A,A11,Opening_Balances!$B:$B),0) | C11: =SUMIFS(Route_Sales!$F:$F,Route_Sales!$C:$C,A11,Route_Sales!$E:$E,"Credit") | D11: =SUMIF(Store_Payments!$B:$B,A11,Store_Payments!$C:$C) | E11: =B11+C11-D11
A12: Store_10 | B12: =IFERROR(SUMIF(Opening_Balances!$A:$A,A12,Opening_Balances!$B:$B),0) | C12: =SUMIFS(Route_Sales!$F:$F,Route_Sales!$C:$C,A12,Route_Sales!$E:$E,"Credit") | D12: =SUMIF(Store_Payments!$B:$B,A12,Store_Payments!$C:$C) | E12: =B12+C12-D12

Sheet Expenses
A1: Date / วันที่ | B1: Category / หมวด | C1: Amount (฿) / จำนวนเงิน | D1: Payment / ช่องทางจ่าย | E1: Vendor or notes / รายละเอียด
A2: 2026-06-16 | B2: Fuel | C2: 800 | D2: Cash | E2: Route 01

Sheet Inventory
A1: Week ending / สิ้นสัปดาห์ | B1: Bags produced / ผลิต | C1: Bags sold / ขาย | D1: Variance / ต่าง
A2: 2026-06-15 | B2: 500 | C2: =SUMIFS(Route_Sales!$D:$D,Route_Sales!$A:$A,">="&A2-6,Route_Sales!$A:$A,"<="&A2) | D2: =B2-C2

Sheet Opening_Balances
A1: Go-live snapshot / ยอดยกมาวันเริ่มใช้
A3: Cash on hand / เงินสด | B3: 0
A4: Bank balance / เงินในบัญชี | B4: 0
A6: Per-store opening debt / ยอดค้างจ่ายยกมา (รายร้าน)
A7: Store / ร้าน | B7: Opening debt (฿) / ยอดค้าง
A8: Store_01 | B8: 0
A9: Store_02 | B9: 0
A10: Store_03 | B10: 0
A11: Store_04 | B11: 0
A12: Store_05 | B12: 0
A13: Store_06 | B13: 0
A14: Store_07 | B14: 0
A15: Store_08 | B15: 0
A16: Store_09 | B16: 0
A17: Store_10 | B17: 0

Sheet Dashboard
A1: Monthly summary / สรุปรายเดือน
A3: Report month (YYYY-MM) / เดือน: | B3: 2026-06
A5: Route cash income / รายได้เงินสด | B5: =SUMIFS(Route_Sales!$F:$F,Route_Sales!$E:$E,"Cash",Route_Sales!$A:$A,">="&DATE(LEFT($B$3,4),RIGHT($B$3,2),1),Route_Sales!$A:$A,"<"&EDATE(DATE(LEFT($B$3,4),RIGHT($B$3,2),1),1))
A6: Route credit income / รายได้ขายเชื่อ | B6: =SUMIFS(Route_Sales!$F:$F,Route_Sales!$E:$E,"Credit",Route_Sales!$A:$A,">="&DATE(LEFT($B$3,4),RIGHT($B$3,2),1),Route_Sales!$A:$A,"<"&EDATE(DATE(LEFT($B$3,4),RIGHT($B$3,2),1),1))
A7: Total route income / รายได้รวม | B7: =B5+B6
A8: Total expenses / ค่าใช้จ่ายรวม | B8: =SUMIFS(Expenses!$C:$C,Expenses!$A:$A,">="&DATE(LEFT($B$3,4),RIGHT($B$3,2),1),Expenses!$A:$A,"<"&EDATE(DATE(LEFT($B$3,4),RIGHT($B$3,2),1),1))
A9: Net (income - expenses) / กำไรสุทธิ | B9: =B7-B8
A11: Top stores still owed / ร้านค้างจ่ายสูงสุด
A12: See Store_Balances tab / ดูแท็บ Store_Balances
A14: Expense breakdown / ค่าใช้จ่ายตามหมวด
A15: Water | B15: =SUMIFS(Expenses!$C:$C,Expenses!$B:$B,"Water",Expenses!$A:$A,">="&DATE(LEFT($B$3,4),RIGHT($B$3,2),1),Expenses!$A:$A,"<"&EDATE(DATE(LEFT($B$3,4),RIGHT($B$3,2),1),1))
A16: Power | B16: =SUMIFS(Expenses!$C:$C,Expenses!$B:$B,"Power",Expenses!$A:$A,">="&DATE(LEFT($B$3,4),RIGHT($B$3,2),1),Expenses!$A:$A,"<"&EDATE(DATE(LEFT($B$3,4),RIGHT($B$3,2),1),1))
A17: Bags | B17: =SUMIFS(Expenses!$C:$C,Expenses!$B:$B,"Bags",Expenses!$A:$A,">="&DATE(LEFT($B$3,4),RIGHT($B$3,2),1),Expenses!$A:$A,"<"&EDATE(DATE(LEFT($B$3,4),RIGHT($B$3,2),1),1))
A18: Machine repair | B18: =SUMIFS(Expenses!$C:$C,Expenses!$B:$B,"Machine repair",Expenses!$A:$A,">="&DATE(LEFT($B$3,4),RIGHT($B$3,2),1),Expenses!$A:$A,"<"&EDATE(DATE(LEFT($B$3,4),RIGHT($B$3,2),1),1))
A19: Fuel | B19: =SUMIFS(Expenses!$C:$C,Expenses!$B:$B,"Fuel",Expenses!$A:$A,">="&DATE(LEFT($B$3,4),RIGHT($B$3,2),1),Expenses!$A:$A,"<"&EDATE(DATE(LEFT($B$3,4),RIGHT($B$3,2),1),1))
A20: Vehicle repair | B20: =SUMIFS(Expenses!$C:$C,Expenses!$B:$B,"Vehicle repair",Expenses!$A:$A,">="&DATE(LEFT($B$3,4),RIGHT($B$3,2),1),Expenses!$A:$A,"<"&EDATE(DATE(LEFT($B$3,4),RIGHT($B$3,2),1),1))
A21: Driver pay | B21: =SUMIFS(Expenses!$C:$C,Expenses!$B:$B,"Driver pay",Expenses!$A:$A,">="&DATE(LEFT($B$3,4),RIGHT($B$3,2),1),Expenses!$A:$A,"<"&EDATE(DATE(LEFT($B$3,4),RIGHT($B$3,2),1),1))
A22: Rent | B22: =SUMIFS(Expenses!$C:$C,Expenses!$B:$B,"Rent",Expenses!$A:$A,">="&DATE(LEFT($B$3,4),RIGHT($B$3,2),1),Expenses!$A:$A,"<"&EDATE(DATE(LEFT($B$3,4),RIGHT($B$3,2),1),1))
A23: Permits | B23: =SUMIFS(Expenses!$C:$C,Expenses!$B:$B,"Permits",Expenses!$A:$A,">="&DATE(LEFT($B$3,4),RIGHT($B$3,2),1),Expenses!$A:$A,"<"&EDATE(DATE(LEFT($B$3,4),RIGHT($B$3,2),1),1))
A24: Insurance | B24: =SUMIFS(Expenses!$C:$C,Expenses!$B:$B,"Insurance",Expenses!$A:$A,">="&DATE(LEFT($B$3,4),RIGHT($B$3,2),1),Expenses!$A:$A,"<"&EDATE(DATE(LEFT($B$3,4),RIGHT($B$3,2),1),1))
A25: Other | B25: =SUMIFS(Expenses!$C:$C,Expenses!$B:$B,"Other",Expenses!$A:$A,">="&DATE(LEFT($B$3,4),RIGHT($B$3,2),1),Expenses!$A:$A,"<"&EDATE(DATE(LEFT($B$3,4),RIGHT($B$3,2),1),1))

Sheet Cash_Flow
A1: Cash flow / กระแสเงินสด
A3: Report month (YYYY-MM): | B3: 2026-06
A5: Opening cash / เงินสดยกมา | B5: =Opening_Balances!B3
A6: Opening bank / เงินธนาคารยกมา | B6: =Opening_Balances!B4
A7: + Route cash collected / + เงินสดจากเส้นทาง | B7: =SUMIFS(Route_Sales!$F:$F,Route_Sales!$E:$E,"Cash",Route_Sales!$A:$A,">="&DATE(LEFT($B$3,4),RIGHT($B$3,2),1),Route_Sales!$A:$A,"<"&EDATE(DATE(LEFT($B$3,4),RIGHT($B$3,2),1),1))
A8: + Store payments (cash) / + รับชำระเงินสด | B8: =SUMIFS(Store_Payments!$C:$C,Store_Payments!$D:$D,"Cash",Store_Payments!$A:$A,">="&DATE(LEFT($B$3,4),RIGHT($B$3,2),1),Store_Payments!$A:$A,"<"&EDATE(DATE(LEFT($B$3,4),RIGHT($B$3,2),1),1))
A9: + Store payments (bank) / + รับชำระโอน | B9: =SUMIFS(Store_Payments!$C:$C,Store_Payments!$D:$D,"Bank",Store_Payments!$A:$A,">="&DATE(LEFT($B$3,4),RIGHT($B$3,2),1),Store_Payments!$A:$A,"<"&EDATE(DATE(LEFT($B$3,4),RIGHT($B$3,2),1),1))
A10: - Cash expenses / - จ่ายเงินสด | B10: =SUMIFS(Expenses!$C:$C,Expenses!$D:$D,"Cash",Expenses!$A:$A,">="&DATE(LEFT($B$3,4),RIGHT($B$3,2),1),Expenses!$A:$A,"<"&EDATE(DATE(LEFT($B$3,4),RIGHT($B$3,2),1),1))
A11: - Bank expenses / - จ่ายโอน/บัญชี | B11: =SUMIFS(Expenses!$C:$C,Expenses!$D:$D,"Bank",Expenses!$A:$A,">="&DATE(LEFT($B$3,4),RIGHT($B$3,2),1),Expenses!$A:$A,"<"&EDATE(DATE(LEFT($B$3,4),RIGHT($B$3,2),1),1))
A12: Expected cash on hand / เงินสดคาดว่า | B12: =B5+B7-B10
A13: Expected bank balance / เงินธนาคารคาดว่า | B13: =B6+B8+B9-B11
